optshare/__init__.py
optshare/dateutils/__init__.py
optshare/dateutils/calendar_def.py
optshare/dateutils/date_utility.py
optshare/index/__init__.py
optshare/index/index_data.py
optshare/market_yield/__init__.py
optshare/market_yield/bond_yield.py
optshare/market_yield/shibor.py
optshare/option/__init__.py
optshare/option/option_data.py
optshare/option/option_info.csv
optshare/option/option_info.py
optshare/quote/__init__.py
optshare/quote/commodity_option.py
optshare/quote/financial_option.py
optshare-0.1.66.dist-info/LICENSE.txt
optshare-0.1.66.dist-info/METADATA
optshare-0.1.66.dist-info/WHEEL
optshare-0.1.66.dist-info/top_level.txt
optshare-0.1.66.dist-info/RECORD
