Metadata-Version: 2.1
Name: optshare
Version: 0.1.66
Summary: Python package for option, index, and yield data
Home-page: https://yulu0131.github.io/
Author: Yu Lu
Author-email: luyudso@gmail.com
License: Free for non-commercial use
Keywords: derivatives,finance
Platform: UNKNOWN
Classifier: Development Status :: 3 - Alpha
Classifier: Programming Language :: Python :: 3.9
Requires-Python: >=3.9
License-File: LICENSE.txt
Requires-Dist: pandas (>=1.4.3)
Requires-Dist: lxml (>=4.9.0)
Requires-Dist: requests
